[{"name":"Dzhaga","id":563692,"country":"RU"},{"name":"Dzerzhinskoye","id":1507035,"country":"RU"},{"name":"Dzorastan","id":174918,"country":"AM"},{"name":"Dzoragyugh","id":616716,"country":"AM"},{"name":"Dzithankov","id":616719,"country":"AM"},{"name":"Dzhida","id":2024579,"country":"RU"},{"name":"Dzhebariki-Khaya","id":2024626,"country":"RU"},{"name":"Dzhayrakh","id":563623,"country":"RU"},{"name":"Dzhalka","id":563678,"country":"RU"},{"name":"Dzerzhinskiy","id":563705,"country":"RU"},{"name":"Dzhandy-Say","id":609968,"country":"KZ"},{"name":"Dzhaindy","id":609991,"country":"KZ"},{"name":"Dzyerawnaya","id":629092,"country":"BY"},{"name":"Dzhankhot","id":563661,"country":"RU"},{"name":"Dzikhch’a","id":823851,"country":"GE"},{"name":"Dzhubka","id":831396,"country":"RU"},{"name":"Dzhubga","id":563601,"country":"RU"},{"name":"Dzhardzhava","id":796931,"country":"UA"},{"name":"Dzhankoy","id":709334,"country":"UA"},{"name":"Dzhaga-Mamysh","id":709344,"country":"UA"},{"name":"Dzhefar-Berdy","id":709325,"country":"UA"},{"name":"Dzerzhinsk","id":2056861,"country":"RU"},{"name":"Dzerzhinsk","id":563708,"country":"RU"},{"name":"Dzhalil","id":563681,"country":"RU"},{"name":"Dzheguta","id":563637,"country":"RU"},{"name":"Dzhiginka","id":563618,"country":"RU"},{"name":"Dzhalagash","id":1524478,"country":"KZ"},{"name":"Dzhambeyty","id":609977,"country":"KZ"},{"name":"Dzitbalche","id":3529650,"country":"MX"},{"name":"Dzan","id":3529672,"country":"MX"},{"name":"Dzilam Gonzalez","id":3529654,"country":"MX"},{"name":"Dzemul","id":3529669,"country":"MX"},{"name":"Dzidzantun","id":3529660,"country":"MX"},{"name":"Dzierżoniów","id":7531351,"country":"PL"},{"name":"Dzierzoniow","id":3099828,"country":"PL"},{"name":"Działdowo","id":7532449,"country":"PL"},{"name":"Dzialdowo","id":772748,"country":"PL"},{"name":"Dzērves","id":460112,"country":"LV"},{"name":"Dz’vinogrud","id":709296,"country":"UA"},{"name":"Dzerzhynsk","id":709354,"country":"UA"},{"name":"Dzyarzhynsk","id":628634,"country":"BY"},{"name":"Dzisna","id":629055,"country":"BY"},{"name":"Dzherovo","id":6460952,"country":"BG"},{"name":"Dzoraghbyur","id":616712,"country":"AM"},{"name":"Dzhalilabad","id":148290,"country":"AZ"},{"name":"Dzuunharaa","id":2031533,"country":"MN"},{"name":"Dzvinogrud","id":709295,"country":"UA"},{"name":"Dzyatlava","id":628658,"country":"BY"},{"name":"Dzagam","id":586692,"country":"AZ"},{"name":"Dzhebel","id":731741,"country":"BG"},{"name":"Dzuiché","id":3529630,"country":"MX"},{"name":"Dziani","id":921897,"country":"KM"},{"name":"Dzhangala","id":609965,"country":"KZ"},{"name":"Dzepciste","id":790857,"country":"MK"},{"name":"Dzuyl","id":1515979,"country":"MN"},{"name":"Dzuunmod","id":1515986,"country":"MN"},{"name":"Dzuunhovoo","id":1515989,"country":"MN"},{"name":"Dzuer","id":1515996,"country":"MN"},{"name":"Dzoolon","id":1515999,"country":"MN"},{"name":"Dzel","id":1516004,"country":"MN"},{"name":"Dzalaa","id":1516023,"country":"MN"},{"name":"Dzag","id":1516036,"country":"MN"},{"name":"Dzadgay","id":1516037,"country":"MN"},{"name":"Dzuunkharaa","id":2030066,"country":"MN"},{"name":"Dzuunmod","id":2031517,"country":"MN"},{"name":"Dzuunbulag","id":2031552,"country":"MN"},{"name":"Dzuunbulag","id":2031553,"country":"MN"},{"name":"Dzogsool","id":2031601,"country":"MN"},{"name":"Dzelter","id":2031613,"country":"MN"},{"name":"Dzegstey","id":2031615,"country":"MN"},{"name":"Dzaanhoshuu","id":2031704,"country":"MN"},{"name":"Dzitas","id":3529652,"country":"MX"},{"name":"Dzwola","id":772641,"country":"PL"},{"name":"Dzwierzuty","id":772644,"country":"PL"},{"name":"Dzikow Stary","id":772658,"country":"PL"},{"name":"Dzikowiec","id":772662,"country":"PL"},{"name":"Dziewin","id":772667,"country":"PL"},{"name":"Dzierzkowice","id":772680,"country":"PL"},{"name":"Dzierzgowo","id":772687,"country":"PL"},{"name":"Dzierzaznia","id":772698,"country":"PL"},{"name":"Dziekanow Lesny","id":772722,"country":"PL"},{"name":"Dzialoszyce","id":772747,"country":"PL"},{"name":"Dziadkowice","id":772758,"country":"PL"},{"name":"Dziecmorowice","id":3099778,"country":"PL"},{"name":"Dziwnow","id":3099783,"country":"PL"},{"name":"Dzierzgon","id":3099842,"country":"PL"},{"name":"Dziergowice","id":3099873,"country":"PL"},{"name":"Dziemiany","id":3099878,"country":"PL"},{"name":"Dziegielow","id":3099887,"country":"PL"},{"name":"Dzialoszyn","id":3099923,"country":"PL"},{"name":"Dziadowa Kloda","id":3099934,"country":"PL"},{"name":"Dzaoudzi","id":921900,"country":"YT"}]