[{"name":"Ishikawa-ken","id":1861387,"country":"JP"},{"name":"Iskandar","id":1513900,"country":"UZ"},{"name":"Isleworth","id":2646004,"country":"GB"},{"name":"Isawa","id":1861454,"country":"JP"},{"name":"Islandia","id":4159872,"country":"US"},{"name":"Ishiwaki","id":2112569,"country":"JP"},{"name":"Ispringen","id":6555704,"country":"DE"},{"name":"Ispringen","id":2895636,"country":"DE"},{"name":"Isfara","id":1514896,"country":"TJ"},{"name":"Istaravshan","id":1220253,"country":"TJ"},{"name":"Isfana","id":1222662,"country":"KG"},{"name":"Ishurdi","id":1185207,"country":"BD"},{"name":"Islamnagar","id":1269670,"country":"IN"},{"name":"Ishiki","id":1861383,"country":"JP"},{"name":"Ishige","id":1861406,"country":"JP"},{"name":"Ishigaki","id":1861416,"country":"JP"},{"name":"Ishikawa","id":2112583,"country":"JP"},{"name":"Isla Vista","id":5359864,"country":"US"},{"name":"Istalif","id":1142330,"country":"AF"},{"name":"Istok","id":1536648,"country":"RU"},{"name":"Istok","id":2023427,"country":"RU"},{"name":"Islington","id":2646003,"country":"GB"},{"name":"Islamic Republic of Iran","id":130758,"country":"IR"},{"name":"Isomura","id":2112562,"country":"JP"},{"name":"Isparta","id":311073,"country":"TR"},{"name":"Iskushuban","id":56505,"country":"SO"},{"name":"Issia","id":2287790,"country":"CI"},{"name":"Isernhagen Farster Bauerschaft","id":2895664,"country":"DE"},{"name":"Ishøj Kommune","id":2619378,"country":"DK"},{"name":"Isser","id":2492991,"country":"DZ"},{"name":"Issoire","id":6440053,"country":"FR"},{"name":"Islington","id":3333156,"country":"GB"},{"name":"Islampur","id":1269665,"country":"IN"},{"name":"Ischia","id":6539811,"country":"IT"},{"name":"Ischia Porto","id":3175453,"country":"IT"},{"name":"Ischia","id":3175458,"country":"IT"},{"name":"Ishikawa","id":1861393,"country":"JP"},{"name":"Ishqoshim","id":1221614,"country":"TJ"},{"name":"Istok","id":789996,"country":"XK"},{"name":"Islamey","id":537344,"country":"RU"},{"name":"Isyangulovo","id":555717,"country":"RU"},{"name":"Issa","id":555798,"country":"RU"},{"name":"Ispravnaya","id":555801,"country":"RU"},{"name":"Ishnya","id":555933,"country":"RU"},{"name":"Ishley","id":555950,"country":"RU"},{"name":"Ishkhoy-Yurt","id":555962,"country":"RU"},{"name":"Ishcherskaya","id":555994,"country":"RU"},{"name":"Isakly","id":556111,"country":"RU"},{"name":"Is","id":556131,"country":"RU"},{"name":"Iskateley","id":866062,"country":"RU"},{"name":"Isetskoye","id":1505466,"country":"RU"},{"name":"Iset","id":1505472,"country":"RU"},{"name":"Istra","id":555746,"country":"RU"},{"name":"Iskan’","id":555904,"country":"RU"},{"name":"Istomino","id":555758,"country":"RU"},{"name":"Islavskoye","id":555832,"country":"RU"},{"name":"Isakovo","id":556087,"country":"RU"},{"name":"Istomikha","id":555765,"country":"RU"},{"name":"Ishino","id":816839,"country":"RU"},{"name":"Istra","id":6417706,"country":"RU"},{"name":"Isaikha","id":556121,"country":"RU"},{"name":"Ismentsy","id":555815,"country":"RU"},{"name":"Isakovo","id":6422790,"country":"RU"},{"name":"Isayevo","id":556025,"country":"RU"},{"name":"Isady","id":556126,"country":"RU"},{"name":"Isakovo","id":556086,"country":"RU"},{"name":"Isar","id":707552,"country":"UA"},{"name":"Istoki","id":707526,"country":"UA"},{"name":"Islamic Republic of Pakistan","id":1168579,"country":"PK"},{"name":"Ishioka","id":2112571,"country":"JP"},{"name":"Istok","id":2023426,"country":"RU"},{"name":"Islamic Republic of Mauritania","id":2378080,"country":"MR"},{"name":"Islamic Republic of Afghanistan","id":1149361,"country":"AF"},{"name":"Isehara","id":1861449,"country":"JP"},{"name":"Isenhour","id":4472818,"country":"US"},{"name":"Istérnia","id":261723,"country":"GR"},{"name":"Isanti County","id":5031493,"country":"US"},{"name":"Isachsen","id":5984185,"country":"CA"},{"name":"Isiro","id":215771,"country":"CD"},{"name":"Island City","id":5733154,"country":"US"},{"name":"Isle of Wight","id":2646007,"country":"GB"},{"name":"Issy-les-Moulineaux","id":6451970,"country":"FR"},{"name":"Issy-les-Moulineaux","id":3012649,"country":"FR"},{"name":"Issyk-Kul’skaya Oblast’","id":1528260,"country":"KG"},{"name":"Island Beach","id":7521909,"country":"AU"},{"name":"Ishimbay","id":555980,"country":"RU"},{"name":"Ishim","id":1505453,"country":"RU"},{"name":"Isil’kul’","id":1505438,"country":"RU"},{"name":"Iska-Chebakova","id":1505432,"country":"RU"},{"name":"Isheyevka","id":555984,"country":"RU"},{"name":"Island Park","id":5257623,"country":"US"},{"name":"Isle of Wight County","id":4766205,"country":"US"},{"name":"Isaac","id":7839587,"country":"AU"},{"name":"Isabella","id":2162583,"country":"AU"},{"name":"Isisford","id":2162577,"country":"AU"},{"name":"Isahaya","id":1861464,"country":"JP"},{"name":"Ishii","id":1861400,"country":"JP"},{"name":"Isesaki","id":1861436,"country":"JP"},{"name":"Ishinomaki","id":2112576,"country":"JP"},{"name":"Isoshi","id":1861336,"country":"JP"},{"name":"Ishikari","id":2129909,"country":"JP"},{"name":"Ise","id":1861450,"country":"JP"},{"name":"Istres","id":6447134,"country":"FR"},{"name":"Istres","id":3012647,"country":"FR"},{"name":"Issac","id":6429402,"country":"FR"},{"name":"Issac","id":3012687,"country":"FR"},{"name":"Isigny-le-Buat","id":6435456,"country":"FR"},{"name":"Isigny-le-Buat","id":3012713,"country":"FR"},{"name":"Isaac","id":3012730,"country":"FR"},{"name":"Isserteaux","id":6440052,"country":"FR"},{"name":"Isserteaux","id":3012668,"country":"FR"},{"name":"Isigny-sur-Mer","id":6427269,"country":"FR"},{"name":"Isigny-sur-Mer","id":3012712,"country":"FR"},{"name":"Isturits","id":6440425,"country":"FR"},{"name":"Isturits","id":3012645,"country":"FR"},{"name":"Isseuges","id":3012667,"country":"FR"},{"name":"Ispoure","id":6440423,"country":"FR"},{"name":"Ispoure","id":3012689,"country":"FR"},{"name":"Isserpent","id":6425368,"country":"FR"},{"name":"Isserpent","id":3012669,"country":"FR"},{"name":"Issor","id":6440424,"country":"FR"},{"name":"Issor","id":3012657,"country":"FR"},{"name":"Issoudun-Létrieix","id":6447741,"country":"FR"},{"name":"Issoudun-Létrieix","id":3012653,"country":"FR"},{"name":"Isernia","id":6540113,"country":"IT"},{"name":"Isernia","id":3175445,"country":"IT"},{"name":"Isola del Giglio","id":6542742,"country":"IT"},{"name":"Isenta","id":2267387,"country":"PT"},{"name":"Isle Pierre","id":5984673,"country":"CA"},{"name":"Isaac Arriaga","id":4025025,"country":"MX"},{"name":"Ishuatan","id":3526769,"country":"MX"},{"name":"Iserlohn","id":2895669,"country":"DE"},{"name":"Isselburg","id":2895630,"country":"DE"},{"name":"Isny im Allgau","id":2895638,"country":"DE"},{"name":"Isselhorst","id":2895628,"country":"DE"},{"name":"Isseroda","id":6550249,"country":"DE"},{"name":"Isseroda","id":2895623,"country":"DE"},{"name":"Issum","id":6553032,"country":"DE"},{"name":"Issum","id":2895617,"country":"DE"},{"name":"Issel","id":2895632,"country":"DE"},{"name":"Isenbüttel","id":6552308,"country":"DE"},{"name":"Isenbuttel","id":2895688,"country":"DE"},{"name":"Isenbruch","id":3205578,"country":"DE"},{"name":"Issing","id":2895618,"country":"DE"},{"name":"Ischert","id":3207527,"country":"DE"},{"name":"Isenburg","id":6553834,"country":"DE"},{"name":"Isenburg","id":2895689,"country":"DE"},{"name":"Istha","id":2895610,"country":"DE"},{"name":"Issersheilingen","id":6549924,"country":"DE"},{"name":"Issersheilingen","id":2895622,"country":"DE"},{"name":"Isterberg","id":6552937,"country":"DE"},{"name":"Isterberg","id":3208432,"country":"DE"},{"name":"Iserlohnerheide","id":2895668,"country":"DE"},{"name":"Isselbach","id":6554046,"country":"DE"},{"name":"Isselbach","id":2895631,"country":"DE"},{"name":"Isenhagen","id":2895683,"country":"DE"},{"name":"Issendorf","id":2895624,"country":"DE"},{"name":"Isterbies","id":2895612,"country":"DE"},{"name":"Isona i Conca Dellà","id":6358860,"country":"ES"},{"name":"Isla Cristina","id":6358218,"country":"ES"},{"name":"Isla Cristina","id":2516431,"country":"ES"},{"name":"Isábena","id":6358356,"country":"ES"},{"name":"Isso","id":2516422,"country":"ES"},{"name":"Isona","id":3120270,"country":"ES"},{"name":"Islares","id":3120275,"country":"ES"},{"name":"Istán","id":6359466,"country":"ES"},{"name":"Istan","id":2516421,"country":"ES"},{"name":"Isasondo","id":3120289,"country":"ES"},{"name":"Isla de Maipo","id":3887072,"country":"CL"},{"name":"Isidro Casanova","id":3433424,"country":"AR"},{"name":"Isla Verde","id":3853643,"country":"AR"},{"name":"Isca Yacú","id":3853689,"country":"AR"},{"name":"Isla Verde","id":3853644,"country":"AR"},{"name":"Island Bay","id":2189506,"country":"NZ"},{"name":"Isaías Coelho","id":3398007,"country":"BR"},{"name":"Islikon","id":2660240,"country":"CH"},{"name":"Iseltwald","id":7286148,"country":"CH"},{"name":"Isérables","id":7286150,"country":"CH"},{"name":"Iserables","id":2660242,"country":"CH"},{"name":"Isorno","id":7286153,"country":"CH"},{"name":"Isenthal","id":7286149,"country":"CH"},{"name":"Isenthal","id":2660244,"country":"CH"},{"name":"Isipingo","id":994493,"country":"ZA"},{"name":"Iseyin","id":2337181,"country":"NG"},{"name":"Isiolo","id":196231,"country":"KE"},{"name":"Istanbul","id":745044,"country":"TR"},{"name":"Isparta","id":311071,"country":"TR"},{"name":"Islahiye","id":311104,"country":"TR"},{"name":"Ispir","id":745047,"country":"TR"},{"name":"Istebník","id":3059775,"country":"SK"},{"name":"Isperikh","id":730866,"country":"BG"},{"name":"Isperikhovo","id":6461132,"country":"BG"},{"name":"Isperikhovo","id":730864,"country":"BG"},{"name":"Ischgl","id":7872579,"country":"AT"},{"name":"Ischgl","id":2775183,"country":"AT"},{"name":"Istmina","id":3680453,"country":"CO"},{"name":"Isle of Man","id":3042225,"country":"IM"},{"name":"Isle of Man","id":6620382,"country":"IM"},{"name":"Istarska Županija","id":3337514,"country":"HR"},{"name":"Iswardi","id":1200682,"country":"BD"},{"name":"isfīr al Maḩaṭṭah","id":250303,"country":"JO"},{"name":"Ishie Town","id":6915258,"country":"NG"},{"name":"Isola di Capo Rizzuto","id":6542239,"country":"IT"},{"name":"Islón","id":3887059,"country":"CL"},{"name":"Islas Agrarias Grupo B","id":3979563,"country":"MX"},{"name":"Island County","id":5798453,"country":"US"},{"name":"Isgett Circle","id":4583090,"country":"US"},{"name":"Isabella County","id":4997272,"country":"US"},{"name":"Ishoj","id":2619377,"country":"DK"},{"name":"Isna","id":355449,"country":"EG"},{"name":"Ismailia","id":361055,"country":"EG"},{"name":"Issoire","id":3012664,"country":"FR"},{"name":"Islampur","id":1269666,"country":"IN"},{"name":"Istgah-e Garmsar","id":32723,"country":"IR"},{"name":"Isieke","id":2337148,"country":"NG"},{"name":"Ise-Ekiti","id":2337207,"country":"NG"},{"name":"Isanlu Itedoijowa","id":2337235,"country":"NG"},{"name":"Isulan","id":1710470,"country":"PH"},{"name":"Isabela","id":1710520,"country":"PH"},{"name":"Isabela","id":1710518,"country":"PH"},{"name":"Islāmābād Capital Territory","id":1162015,"country":"PK"},{"name":"Islamabad","id":1176615,"country":"PK"},{"name":"Iskitim","id":1505429,"country":"RU"},{"name":"Iskenderun","id":311111,"country":"TR"},{"name":"Iskilip","id":745076,"country":"TR"},{"name":"Isaka","id":159045,"country":"TZ"},{"name":"Iselin","id":5099738,"country":"US"},{"name":"Islip","id":5122413,"country":"US"},{"name":"Issaquah","id":5798487,"country":"US"},{"name":"Ispas","id":707529,"country":"UA"},{"name":"Ismayilli Rayon","id":586320,"country":"AZ"},{"name":"Ismayilli","id":586318,"country":"AZ"},{"name":"Iskur","id":728348,"country":"BG"},{"name":"Isla del Sol","id":3913985,"country":"BO"},{"name":"Iscuande","id":3680491,"country":"CO"},{"name":"Isnos","id":3792389,"country":"CO"},{"name":"Issigau","id":6556802,"country":"DE"},{"name":"Issigau","id":2895619,"country":"DE"},{"name":"Ismaning","id":6556317,"country":"DE"},{"name":"Ismaning","id":2895643,"country":"DE"},{"name":"Isert","id":6553408,"country":"DE"},{"name":"Isert","id":2895659,"country":"DE"},{"name":"Isen","id":2895702,"country":"DE"},{"name":"Isuerre","id":6362817,"country":"ES"},{"name":"Isuerre","id":3120263,"country":"ES"},{"name":"Isòvol","id":6357608,"country":"ES"},{"name":"Isovol","id":3120272,"country":"ES"},{"name":"Iscar","id":3120288,"country":"ES"},{"name":"Isar","id":6356470,"country":"ES"},{"name":"Isar","id":3120292,"country":"ES"},{"name":"Isokyrö","id":656457,"country":"FI"},{"name":"Isokyro","id":656456,"country":"FI"},{"name":"Isojoki","id":656518,"country":"FI"},{"name":"Isojoki","id":656517,"country":"FI"},{"name":"Is-sur-Tille","id":3012652,"country":"FR"},{"name":"Issoudun","id":3012655,"country":"FR"},{"name":"Issou","id":3012656,"country":"FR"},{"name":"Issenheim","id":3012671,"country":"FR"},{"name":"Isse","id":3012676,"country":"FR"},{"name":"Isques","id":3012688,"country":"FR"},{"name":"Isneauville","id":3012698,"country":"FR"},{"name":"Isle","id":3012709,"country":"FR"},{"name":"Isbergues","id":3012725,"country":"FR"},{"name":"Isleham","id":2646012,"country":"GB"},{"name":"Isle Of Mull","id":7290043,"country":"GB"},{"name":"Istiaia","id":261720,"country":"GR"},{"name":"Isthmia","id":261721,"country":"GR"},{"name":"Isaszeg","id":3051077,"country":"HU"},{"name":"Isimu","id":1642996,"country":"ID"},{"name":"Isagarh","id":1269685,"country":"IN"},{"name":"Isafjoerdur","id":3415667,"country":"IS"},{"name":"Ispica","id":2524493,"country":"IT"},{"name":"Isola delle Femmine","id":2524494,"country":"IT"},{"name":"Isola Capo Rizzuto","id":2524495,"country":"IT"},{"name":"Isnello","id":2524496,"country":"IT"},{"name":"Isili","id":2524498,"country":"IT"},{"name":"Isca sullo Ionio","id":2524501,"country":"IT"},{"name":"Istrana","id":3175398,"country":"IT"},{"name":"Issogne","id":3175403,"country":"IT"},{"name":"Issime","id":3175405,"country":"IT"},{"name":"Ispra","id":3175406,"country":"IT"},{"name":"Isorella","id":3175408,"country":"IT"},{"name":"Isola Vicentina","id":3175414,"country":"IT"},{"name":"Isola SantAntonio","id":3175415,"country":"IT"},{"name":"Isola Dovarese","id":3175424,"country":"IT"},{"name":"Isola del Piano","id":3175426,"country":"IT"},{"name":"Isola del Liri","id":3175427,"country":"IT"},{"name":"Isola della Scala","id":3175428,"country":"IT"},{"name":"Isola del Gran Sasso dItalia","id":3175429,"country":"IT"},{"name":"Isola del Cantone","id":3175430,"country":"IT"},{"name":"Isolabona","id":3175433,"country":"IT"},{"name":"Iseo","id":3175447,"country":"IT"},{"name":"Ischitella","id":3175452,"country":"IT"},{"name":"Ischia di Castro","id":3175454,"country":"IT"},{"name":"Isola dAsti","id":6534388,"country":"IT"},{"name":"Isola di Fondra","id":6534508,"country":"IT"},{"name":"Isola del Giglio","id":6534705,"country":"IT"},{"name":"Isole Tremiti","id":6534807,"country":"IT"},{"name":"Isera","id":6534997,"country":"IT"},{"name":"Isso","id":6535172,"country":"IT"},{"name":"Isolabella","id":6535397,"country":"IT"},{"name":"Issiglio","id":6535398,"country":"IT"},{"name":"Ispani","id":6535553,"country":"IT"},{"name":"Isola Rizza","id":6535574,"country":"IT"},{"name":"Isasca","id":6535862,"country":"IT"},{"name":"Islington","id":3489962,"country":"JM"},{"name":"Isseksi","id":2545436,"country":"MA"},{"name":"Isla Mujeres","id":3526756,"country":"MX"},{"name":"Isla de Aguada","id":3526766,"country":"MX"},{"name":"Isla Soyaltepec","id":3801262,"country":"MX"},{"name":"Isla del Bosque","id":3976232,"country":"MX"},{"name":"Isara","id":2337227,"country":"NG"},{"name":"Isdalssto","id":3151001,"country":"NO"},{"name":"Isla Bastimentos","id":3714260,"country":"PA"},{"name":"Isugod","id":1710473,"country":"PH"},{"name":"Isla","id":1710489,"country":"PH"},{"name":"Isabel","id":1710523,"country":"PH"},{"name":"Isabang","id":1710526,"country":"PH"},{"name":"Islamkot","id":1176608,"country":"PK"},{"name":"Istebna","id":3097865,"country":"PL"},{"name":"Isabel Segunda","id":4565575,"country":"PR"},{"name":"Isabela","id":4565577,"country":"PR"},{"name":"Isla Pucu","id":3437962,"country":"PY"},{"name":"Isverna","id":675462,"country":"RO"},{"name":"Istria","id":675471,"country":"RO"},{"name":"Islaz","id":675480,"country":"RO"},{"name":"Isalnita","id":675489,"country":"RO"},{"name":"Isaccea","id":675495,"country":"RO"},{"name":"Ismoili Somoni","id":1220862,"country":"TJ"},{"name":"Iscehisar","id":311193,"country":"TR"},{"name":"Isiklar","id":439221,"country":"TR"},{"name":"Issenye","id":158974,"country":"TZ"},{"name":"Isingiro","id":7911405,"country":"UG"},{"name":"Islamorada","id":4159839,"country":"US"},{"name":"Isle of Hope","id":4202308,"country":"US"},{"name":"Island Heights","id":4502420,"country":"US"},{"name":"Isle of Palms","id":4583114,"country":"US"},{"name":"Isle of Wight","id":4766204,"country":"US"},{"name":"Island Lake","id":4897579,"country":"US"},{"name":"Ishpeming","id":4997281,"country":"US"},{"name":"Isanti","id":5031489,"country":"US"},{"name":"Island Park","id":5122397,"country":"US"},{"name":"Islandia","id":5122409,"country":"US"},{"name":"Islip Terrace","id":5122417,"country":"US"},{"name":"Isidoro Noblia","id":3442299,"country":"UY"},{"name":"Ishtixon","id":1217215,"country":"UZ"},{"name":"Isangel","id":2136825,"country":"VU"},{"name":"Isniq","id":790002,"country":"XK"},{"name":"Isoka","id":916668,"country":"ZM"}]