[{"name":"Rybatskiy","id":500023,"country":"RU"},{"name":"Ryton","id":7297739,"country":"GB"},{"name":"Ryugasaki","id":2111258,"country":"JP"},{"name":"Ryde","id":2150767,"country":"AU"},{"name":"Rypin","id":7531610,"country":"PL"},{"name":"Rypin","id":3086511,"country":"PL"},{"name":"Rybnik","id":7530790,"country":"PL"},{"name":"Rybnik","id":7531758,"country":"PL"},{"name":"Ryde","id":7839769,"country":"AU"},{"name":"Ryde","id":7299167,"country":"GB"},{"name":"Rychnov nad Kneznou","id":3066503,"country":"CZ"},{"name":"Ryuo","id":1853354,"country":"JP"},{"name":"Ryotsu","id":1853371,"country":"JP"},{"name":"Ryzdvyanyy","id":499811,"country":"RU"},{"name":"Ryabovo","id":500184,"country":"RU"},{"name":"Ryzhkovo","id":6415561,"country":"RU"},{"name":"Ryblovo","id":816711,"country":"RU"},{"name":"Ryazanovka","id":817062,"country":"RU"},{"name":"Ryazanskaya Oblast’","id":500059,"country":"RU"},{"name":"Rybushkino","id":499950,"country":"RU"},{"name":"Ryazan’","id":500095,"country":"RU"},{"name":"Ryazanovskiy","id":500065,"country":"RU"},{"name":"Rychkovo","id":499938,"country":"RU"},{"name":"Ryleyevo","id":499906,"country":"RU"},{"name":"Rybaki","id":500034,"country":"RU"},{"name":"Ryazantsy","id":500054,"country":"RU"},{"name":"Ryabinki","id":500240,"country":"RU"},{"name":"Ryazan","id":500096,"country":"RU"},{"name":"Rybnoye","id":499975,"country":"RU"},{"name":"Ryzhkovichi","id":622455,"country":"BY"},{"name":"Rybatskaya","id":500024,"country":"RU"},{"name":"Rynok","id":499874,"country":"RU"},{"name":"Ryazanskiy","id":508751,"country":"RU"},{"name":"Ryabinovka","id":500228,"country":"RU"},{"name":"Rykhlovskogo","id":2017336,"country":"RU"},{"name":"Rybache","id":695053,"country":"UA"},{"name":"Rybushki","id":7601533,"country":"RU"},{"name":"Ryadnoye","id":500149,"country":"RU"},{"name":"Rynkova Ye. V.","id":1493308,"country":"RU"},{"name":"Ryedale District","id":7290610,"country":"GB"},{"name":"Rynki","id":1493314,"country":"RU"},{"name":"Rybinsk","id":500004,"country":"RU"},{"name":"Ryazanskaya","id":500060,"country":"RU"},{"name":"Rybnaya Sloboda","id":499987,"country":"RU"},{"name":"Rynkova F.","id":1493313,"country":"RU"},{"name":"Ryazansk","id":1493378,"country":"RU"},{"name":"Ryabinki","id":812136,"country":"RU"},{"name":"Rylsk","id":695019,"country":"RU"},{"name":"Rydalmere","id":2150768,"country":"AU"},{"name":"Rylstone","id":2150763,"country":"AU"},{"name":"Rywung","id":2150757,"country":"AU"},{"name":"Rydal","id":2150769,"country":"AU"},{"name":"Rye Park","id":2150764,"country":"AU"},{"name":"Ryes","id":6427411,"country":"FR"},{"name":"Ryes","id":2982095,"country":"FR"},{"name":"Ryde","id":2638911,"country":"GB"},{"name":"Rycroft","id":6136875,"country":"CA"},{"name":"Ryerson","id":6136906,"country":"CA"},{"name":"Ryth","id":2842732,"country":"DE"},{"name":"Rysum","id":2842735,"country":"DE"},{"name":"Ryefield","id":2961645,"country":"IE"},{"name":"Rylane Cross","id":2961642,"country":"IE"},{"name":"Ry Massart","id":2787495,"country":"BE"},{"name":"Ryki","id":7533198,"country":"PL"},{"name":"Ryki","id":759852,"country":"PL"},{"name":"Ryglice","id":7533072,"country":"PL"},{"name":"Ryglice","id":759859,"country":"PL"},{"name":"Rydułtowy","id":7531108,"country":"PL"},{"name":"Rydultowy","id":3086531,"country":"PL"},{"name":"Rychwał","id":7533429,"country":"PL"},{"name":"Rychwal","id":3086541,"country":"PL"},{"name":"Rybna","id":3086591,"country":"PL"},{"name":"Ryem","id":3140840,"country":"NO"},{"name":"Ryton","id":2638894,"country":"GB"},{"name":"Rybnik","id":3086586,"country":"PL"},{"name":"Ryazhsk","id":500047,"country":"RU"},{"name":"Rye","id":5134693,"country":"US"},{"name":"Rykhtichi","id":695026,"country":"UA"},{"name":"Rybakivka","id":695052,"country":"UA"},{"name":"Rymarov","id":3066483,"country":"CZ"},{"name":"Rychvald","id":3066492,"country":"CZ"},{"name":"Rybitvi","id":3066536,"country":"CZ"},{"name":"Rybi","id":3066537,"country":"CZ"},{"name":"Ryomgard","id":2614353,"country":"DK"},{"name":"Ry","id":2614387,"country":"DK"},{"name":"Rymattyla","id":638582,"country":"FI"},{"name":"Ryton on Dunsmore","id":2638892,"country":"GB"},{"name":"Ryhill","id":2638901,"country":"GB"},{"name":"Ryhall","id":2638902,"country":"GB"},{"name":"Rye","id":2638909,"country":"GB"},{"name":"Rypefjord","id":847634,"country":"NO"},{"name":"Rygge","id":3140825,"country":"NO"},{"name":"Ryggebyen","id":3336590,"country":"NO"},{"name":"Rytwiany","id":759814,"country":"PL"},{"name":"Rytro","id":759815,"country":"PL"},{"name":"Ryn","id":759839,"country":"PL"},{"name":"Rymanow","id":759843,"country":"PL"},{"name":"Ryczywol","id":759875,"country":"PL"},{"name":"Rybno","id":759895,"country":"PL"},{"name":"Rybie","id":759915,"country":"PL"},{"name":"Rybczewice","id":759922,"country":"PL"},{"name":"Ryman","id":3086523,"country":"PL"},{"name":"Ryjewo","id":3086524,"country":"PL"},{"name":"Rydzyna","id":3086527,"country":"PL"},{"name":"Ryczywol","id":3086533,"country":"PL"},{"name":"Ryczow","id":3086536,"country":"PL"},{"name":"Rychtal","id":3086544,"country":"PL"},{"name":"Rycerka Gorna","id":3086565,"country":"PL"},{"name":"Rycerka Dolna","id":3086566,"country":"PL"},{"name":"Rybno","id":3086574,"country":"PL"},{"name":"Rybarzowice","id":3086608,"country":"PL"},{"name":"Rydsgard","id":2680959,"country":"SE"},{"name":"Rydeback","id":2680969,"country":"SE"},{"name":"Rydaholm","id":2680977,"country":"SE"},{"name":"Ryd","id":2680985,"country":"SE"},{"name":"Ryland Heights","id":4307052,"country":"US"},{"name":"Rye","id":5092018,"country":"US"},{"name":"Rye Brook","id":5134696,"country":"US"},{"name":"Ryegate","id":5675156,"country":"US"},{"name":"Ry","id":6453496,"country":"FR"},{"name":"Ry","id":2982098,"country":"FR"}]