[{"name":"Xetna","id":3514531,"country":"MX"},{"name":"Xermade","id":6359182,"country":"ES"},{"name":"Xeraco,Jaraco","id":2516372,"country":"ES"},{"name":"Xexéu","id":3384930,"country":"BR"},{"name":"Xenia","id":4528810,"country":"US"},{"name":"Xegar","id":1279749,"country":"CN"},{"name":"Xeri","id":145981,"country":"CY"},{"name":"Xeresa","id":6362011,"country":"ES"},{"name":"Xeresa","id":2516330,"country":"ES"},{"name":"Xertigny","id":6445810,"country":"FR"},{"name":"Xertigny","id":2967269,"country":"FR"},{"name":"Xewkija","id":2562274,"country":"MT"}]